<?xml version="1.0"?>
<object name="portal_catalog">

  <index name="category" meta_type="KeywordIndex">
    <indexed_attr value="category"/>
  </index>
  <index name="exclude_from_parent_listing" meta_type="BooleanIndex">
    <indexed_attr value="exclude_from_parent_listing"/>
  </index>
  <index name="related_quickaccess" meta_type="FieldIndex">
    <indexed_attr value="related_quickaccess"/>
  </index>
  <index name="category_and_topics" meta_type="KeywordIndex">
    <indexed_attr value="category_and_topics"/>
  </index>
  <column value="category_and_topics"/>
  <column value="category"/>
  <column value="exclude_from_parent_listing"/>
  <column value="related_quickaccess"/>

  <!-- Remove imio.smartweb.common breadcrumb index, which is not needed -->
  <index name="breadcrumb" remove="True"/>
  <column value="breadcrumb" remove="True"/>

</object>
